syntopy/Aperture.py
syntopy/Cell.py
syntopy/CellComplex.py
syntopy/Cluster.py
syntopy/Color.py
syntopy/Context.py
syntopy/DGL.py
syntopy/Dictionary.py
syntopy/Edge.py
syntopy/EnergyModel.py
syntopy/Face.py
syntopy/Graph.py
syntopy/Grid.py
syntopy/Helper.py
syntopy/Honeybee.py
syntopy/Matrix.py
syntopy/Neo4j.py
syntopy/Plotly.py
syntopy/Polyskel.py
syntopy/Shell.py
syntopy/Speckle.py
syntopy/Topology.py
syntopy/Vector.py
syntopy/Vertex.py
syntopy/Wire.py
syntopy/__init__.py
syntopy/bin/linux/topologic/__init__.py
syntopy/bin/linux/topologic/topologic.cpython-310-x86_64-linux-gnu.so
syntopy/bin/linux/topologic/topologic.cpython-311-x86_64-linux-gnu.so
syntopy/bin/linux/topologic/topologic.cpython-38-x86_64-linux-gnu.so
syntopy/bin/linux/topologic/topologic.cpython-39-x86_64-linux-gnu.so
syntopy/bin/linux/topologic.libs/libTKBO-6bdf205d.so.7.7.0
syntopy/bin/linux/topologic.libs/libTKBRep-2960a069.so.7.7.0
syntopy/bin/linux/topologic.libs/libTKBool-c44b74bd.so.7.7.0
syntopy/bin/linux/topologic.libs/libTKFillet-9a670ba0.so.7.7.0
syntopy/bin/linux/topologic.libs/libTKG2d-8f31849e.so.7.7.0
syntopy/bin/linux/topologic.libs/libTKG3d-4c6bce57.so.7.7.0
syntopy/bin/linux/topologic.libs/libTKGeomAlgo-26066fd9.so.7.7.0
syntopy/bin/linux/topologic.libs/libTKGeomBase-2116cabe.so.7.7.0
syntopy/bin/linux/topologic.libs/libTKMath-72572fa8.so.7.7.0
syntopy/bin/linux/topologic.libs/libTKMesh-2a060427.so.7.7.0
syntopy/bin/linux/topologic.libs/libTKOffset-6cab68ff.so.7.7.0
syntopy/bin/linux/topologic.libs/libTKPrim-eb1262b3.so.7.7.0
syntopy/bin/linux/topologic.libs/libTKShHealing-e67e5cc7.so.7.7.0
syntopy/bin/linux/topologic.libs/libTKTopAlgo-e4c96c33.so.7.7.0
syntopy/bin/linux/topologic.libs/libTKernel-fb7fe3b7.so.7.7.0
syntopy/bin/linux/topologic.libs/libgcc_s-32c1665e.so.1
syntopy/bin/linux/topologic.libs/libstdc++-672d7b41.so.6.0.30
syntopy/bin/windows/topologic/TKBO-f6b191de.dll
syntopy/bin/windows/topologic/TKBRep-e56a600e.dll
syntopy/bin/windows/topologic/TKBool-7b8d47ae.dll
syntopy-0.0.2.dist-info/LICENSE
syntopy-0.0.2.dist-info/METADATA
syntopy-0.0.2.dist-info/WHEEL
syntopy-0.0.2.dist-info/top_level.txt
syntopy-0.0.2.dist-info/RECORD
