Metadata-Version: 2.1
Name: syntopy
Version: 0.0.2
Summary: An Advanced Spatial Modelling and Analysis Software Library for Architecture, Engineering, and Construction.
Author-email: Syntopy <info@syntopy.io>
Project-URL: Homepage, https://github.com/wassimj/Syntopy
Project-URL: Bug Tracker, https://github.com/wassimj/Syntopy/issues
Project-URL: Documentation, https://syntopy.io
Classifier: Programming Language :: Python :: 3
Classifier: License :: OSI Approved :: GNU General Public License v3 (GPLv3)
Classifier: Operating System :: OS Independent
Requires-Python: >=3.8
License-File: LICENSE
Requires-Dist: numpy
Requires-Dist: tqdm
Requires-Dist: plotly
